TransientAnalyzer/EMOneDimGaussian.py
TransientAnalyzer/LinearGibbs.py
TransientAnalyzer/TransientAnalyzer.py
TransientAnalyzer/__init__.py
TransientAnalyzer-1.2.dist-info/LICENSE
TransientAnalyzer-1.2.dist-info/METADATA
TransientAnalyzer-1.2.dist-info/WHEEL
TransientAnalyzer-1.2.dist-info/top_level.txt
TransientAnalyzer-1.2.dist-info/RECORD
