Metadata-Version: 2.1
Name: TransientAnalyzer
Version: 1.2
Summary: Gaussian process regression-based analysis of noisy transient signals.
Author-email: "Iuliia Baglaeva, Bogdan Iaparov, Ivan Zahradník, Alexandra Zahradníková" <iuliia.baglaeva@savba.sk>
License: MIT License
Project-URL: Homepage, https://github.com/IuliiaBaglaeva/TransientAnalyzer
Project-URL: Bug Tracker, https://github.com/IuliiaBaglaeva/TransientAnalyzer/issues
Classifier: Programming Language :: Python :: 3
Classifier: License :: OSI Approved :: MIT License
Classifier: Operating System :: OS Independent
Requires-Python: >=3.7
License-File: LICENSE
Requires-Dist: gpflow
Requires-Dist: pandas
Requires-Dist: numpy
Requires-Dist: scipy
Requires-Dist: pybaselines
Requires-Dist: importlib-metadata ; python_version >= "3.7"
